grdpcli/__init__.py
grdpcli/cmd_exec.py
grdpcli/help_content.py
grdpcli/variables.py
kpischanskyi-3.0.2.data/data/__init__.py
kpischanskyi-3.0.2.data/data/cmd_exec.py
kpischanskyi-3.0.2.data/data/help_content.py
kpischanskyi-3.0.2.data/data/variables.py
kpischanskyi-3.0.2.data/data/share/grdpcli/grdpcli/.version
kpischanskyi-3.0.2.data/data/share/grdpcli/grdpcli/__init__.py
kpischanskyi-3.0.2.data/data/share/grdpcli/grdpcli/cmd_exec.py
kpischanskyi-3.0.2.data/data/share/grdpcli/grdpcli/help_content.py
kpischanskyi-3.0.2.data/data/share/grdpcli/grdpcli/variables.py
kpischanskyi-3.0.2.data/scripts/grdp
kpischanskyi-3.0.2.dist-info/METADATA
kpischanskyi-3.0.2.dist-info/WHEEL
kpischanskyi-3.0.2.dist-info/top_level.txt
kpischanskyi-3.0.2.dist-info/RECORD
