Metadata-Version: 2.1
Name: kpischanskyi
Version: 3.0.2
Summary: Gitlab Rapid Development Platform CLI client
Home-page: https://test.com
Author: test
Author-email: kostiantyn.pischanskyi@onix-systems.com
Requires-Python: >=3
Requires-Dist: GitPython ==3.1.24
Requires-Dist: requests ==2.27.1
Requires-Dist: tabulate ==0.9.0
Requires-Dist: grdp-cli-kubernetes ==1.0.2
Requires-Dist: rich ==10.16.2
Requires-Dist: questionary ==2.0.1
